
{
    "result": 1,
    "data": [
        {
            "Day": "Day1",
            "H1_00mm": "D1 1:00 o'Clock",
            "H2_00mm": "D1 2:00 o'Clock",
            "H3_00mm": "D1 3:00 o'Clock",
            "H4_00mm":"D1 4:00 o'Clock",
            "H5_00mm": "D1 5:00 o'Clock",
            "H6_00mm": "D1 6:00 o'Clock",
            "H7_00mm": "D1 7:00 o'Clock",
            "H8_00mm": "D1 8:00 o'Clock",
            "H9_00mm": "D1 9:00 o'Clock",
            "H10_00mm": "D1 10:00 o'Clock",
            "H11_00mm": "D1 11:00 o'Clock",
            "H12_00mm": "D1 12:00 o'Clock"
            
        },
        {
            "Day": "Day2",
            "H1_00mm": "D2 1:00 o'Clock",
            "H2_00mm": "D2 2:00 o'Clock",
            "H3_00mm": "D2 3:00 o'Clock",
            "H4_00mm":"D2 4:00 o'Clock",
            "H5_00mm": "D2 5:00 o'Clock",
            "H6_00mm": "D2 6:00 o'Clock",
            "H7_00mm": "D2 7:00 o'Clock",
            "H8_00mm": "D2 8:00 o'Clock",
            "H9_00mm": "D2 9:00 o'Clock",
            "H10_00mm": "D2 10:00 o'Clock",
            "H11_00mm": "D2 11:00 o'Clock",
            "H12_00mm": "D2 12:00 o'Clock"
            
        },
        {
            "Day": "Day3",
            "H1_00mm": "D3 1:00 o'Clock",
            "H2_00mm": "D3 2:00 o'Clock",
            "H3_00mm": "D3 3:00 o'Clock",
            "H4_00mm":"D3 4:00 o'Clock",
            "H5_00mm": "D3 5:00 o'Clock",
            "H6_00mm": "D3 6:00 o'Clock",
            "H7_00mm": "D3 7:00 o'Clock",
            "H8_00mm": "D3 8:00 o'Clock",
            "H9_00mm": "D3 9:00 o'Clock",
            "H10_00mm": "D3 10:00 o'Clock",
            "H11_00mm": "D3 11:00 o'Clock",
            "H12_00mm": "D3 12:00 o'Clock"
            
        },
        {
            "Day": "Day4",
            "H1_00mm": "D4 1:00 o'Clock",
            "H2_00mm": "D4 2:00 o'Clock",
            "H3_00mm": "D4 3:00 o'Clock",
            "H4_00mm":"D4 4:00 o'Clock",
            "H5_00mm": "D4 5:00 o'Clock",
            "H6_00mm": "D4 6:00 o'Clock",
            "H7_00mm": "D4 7:00 o'Clock",
            "H8_00mm": "D4 8:00 o'Clock",
            "H9_00mm": "D4 9:00 o'Clock",
            "H10_00mm": "D4 10:00 o'Clock",
            "H11_00mm": "D4 11:00 o'Clock",
            "H12_00mm": "D4 12:00 o'Clock"
            
        },
        {
            "Day": "Day5",
            "H1_00mm": "D5 1:00 o'Clock",
            "H2_00mm": "D5 2:00 o'Clock",
            "H3_00mm": "D5 3:00 o'Clock",
            "H4_00mm":"D5 4:00 o'Clock",
            "H5_00mm": "D5 5:00 o'Clock",
            "H6_00mm": "D5 6:00 o'Clock",
            "H7_00mm": "D5 7:00 o'Clock",
            "H8_00mm": "D5 8:00 o'Clock",
            "H9_00mm": "D5 9:00 o'Clock",
            "H10_00mm": "D5 10:00 o'Clock",
            "H11_00mm": "D5 11:00 o'Clock",
            "H12_00mm": "D5 12:00 o'Clock"
            
        },
        {
            "Day": "Day6",
            "H1_00mm": "D6 1:00 o'Clock",
            "H2_00mm": "D6 2:00 o'Clock",
            "H3_00mm": "D6 3:00 o'Clock",
            "H4_00mm":"D6 4:00 o'Clock",
            "H5_00mm": "D6 5:00 o'Clock",
            "H6_00mm": "D6 6:00 o'Clock",
            "H7_00mm": "D6 7:00 o'Clock",
            "H8_00mm": "D6 8:00 o'Clock",
            "H9_00mm": "D6 9:00 o'Clock",
            "H10_00mm": "D6 10:00 o'Clock",
            "H11_00mm": "D6 11:00 o'Clock",
            "H12_00mm": "D6 12:00 o'Clock"
            
        },
        {
            "Day": "Day7",
            "H1_00mm": "D7 1:00 o'Clock",
            "H2_00mm": "D7 2:00 o'Clock",
            "H3_00mm": "D7 3:00 o'Clock",
            "H4_00mm":"D7 4:00 o'Clock",
            "H5_00mm": "D7 5:00 o'Clock",
            "H6_00mm": "D7 6:00 o'Clock",
            "H7_00mm": "D7 7:00 o'Clock",
            "H8_00mm": "D7 8:00 o'Clock",
            "H9_00mm": "D7 9:00 o'Clock",
            "H10_00mm": "D7 10:00 o'Clock",
            "H11_00mm": "D7 11:00 o'Clock",
            "H12_00mm": "D7 12:00 o'Clock"
            
        },
        {
            "Day": "Day8",
            "H1_00mm": "D8 1:00 o'Clock",
            "H2_00mm": "D8 2:00 o'Clock",
            "H3_00mm": "D8 3:00 o'Clock",
            "H4_00mm":"D8 4:00 o'Clock",
            "H5_00mm": "D8 5:00 o'Clock",
            "H6_00mm": "D8 6:00 o'Clock",
            "H7_00mm": "D8 7:00 o'Clock",
            "H8_00mm": "D8 8:00 o'Clock",
            "H9_00mm": "D8 9:00 o'Clock",
            "H10_00mm": "D8 10:00 o'Clock",
            "H11_00mm": "D8 11:00 o'Clock",
            "H12_00mm": "D8 12:00 o'Clock"
            
        },
        {
            "Day": "Day9",
            "H1_00mm": "D9 1:00 o'Clock",
            "H2_00mm": "D9 2:00 o'Clock",
            "H3_00mm": "D9 3:00 o'Clock",
            "H4_00mm":"D9 4:00 o'Clock",
            "H5_00mm": "D9 5:00 o'Clock",
            "H6_00mm": "D9 6:00 o'Clock",
            "H7_00mm": "D9 7:00 o'Clock",
            "H8_00mm": "D9 8:00 o'Clock",
            "H9_00mm": "D9 9:00 o'Clock",
            "H10_00mm": "D9 10:00 o'Clock",
            "H11_00mm": "D9 11:00 o'Clock",
            "H12_00mm": "D9 12:00 o'Clock"
            
        },
        {
            "Day": "Day10",
            "H1_00mm": "D10 1:00 o'Clock",
            "H2_00mm": "D10 2:00 o'Clock",
            "H3_00mm": "D10 3:00 o'Clock",
            "H4_00mm":"D10 4:00 o'Clock",
            "H5_00mm": "D10 5:00 o'Clock",
            "H6_00mm": "D10 6:00 o'Clock",
            "H7_00mm": "D10 7:00 o'Clock",
            "H8_00mm": "D10 8:00 o'Clock",
            "H9_00mm": "D10 9:00 o'Clock",
            "H10_00mm": "D10 10:00 o'Clock",
            "H11_00mm": "D10 11:00 o'Clock",
            "H12_00mm": "D10 12:00 o'Clock"
            
        },
        {
            "Day": "Day11",
            "H1_00mm": "D11 1:00 o'Clock",
            "H2_00mm": "D11 2:00 o'Clock",
            "H3_00mm": "D11 3:00 o'Clock",
            "H4_00mm":"D11 4:00 o'Clock",
            "H5_00mm": "D11 5:00 o'Clock",
            "H6_00mm": "D11 6:00 o'Clock",
            "H7_00mm": "D11 7:00 o'Clock",
            "H8_00mm": "D11 8:00 o'Clock",
            "H9_00mm": "D11 9:00 o'Clock",
            "H10_00mm": "D11 10:00 o'Clock",
            "H11_00mm": "D11 11:00 o'Clock",
            "H12_00mm": "D11 12:00 o'Clock"
            
        },
        {
            "Day": "Day12",
            "H1_00mm": "D12 1:00 o'Clock",
            "H2_00mm": "D12 2:00 o'Clock",
            "H3_00mm": "D12 3:00 o'Clock",
            "H4_00mm":"D12 4:00 o'Clock",
            "H5_00mm": "D12 5:00 o'Clock",
            "H6_00mm": "D12 6:00 o'Clock",
            "H7_00mm": "D12 7:00 o'Clock",
            "H8_00mm": "D12 8:00 o'Clock",
            "H9_00mm": "D12 9:00 o'Clock",
            "H10_00mm": "D12 10:00 o'Clock",
            "H11_00mm": "D12 11:00 o'Clock",
            "H12_00mm": "D12 12:00 o'Clock"
            
        },
        {
            "Day": "Day13",
            "H1_00mm": "D13 1:00 o'Clock",
            "H2_00mm": "D13 2:00 o'Clock",
            "H3_00mm": "D13 3:00 o'Clock",
            "H4_00mm":"D13 4:00 o'Clock",
            "H5_00mm": "D13 5:00 o'Clock",
            "H6_00mm": "D13 6:00 o'Clock",
            "H7_00mm": "D13 7:00 o'Clock",
            "H8_00mm": "D13 8:00 o'Clock",
            "H9_00mm": "D13 9:00 o'Clock",
            "H10_00mm": "D13 10:00 o'Clock",
            "H11_00mm": "D13 11:00 o'Clock",
            "H12_00mm": "D13 12:00 o'Clock"
            
        },
        {
            "Day": "Day14",
            "H1_00mm": "D14 1:00 o'Clock",
            "H2_00mm": "D14 2:00 o'Clock",
            "H3_00mm": "D14 3:00 o'Clock",
            "H4_00mm":"D14 4:00 o'Clock",
            "H5_00mm": "D14 5:00 o'Clock",
            "H6_00mm": "D14 6:00 o'Clock",
            "H7_00mm": "D14 7:00 o'Clock",
            "H8_00mm": "D14 8:00 o'Clock",
            "H9_00mm": "D14 9:00 o'Clock",
            "H10_00mm": "D14 10:00 o'Clock",
            "H11_00mm": "D14 11:00 o'Clock",
            "H12_00mm": "D14 12:00 o'Clock"
            
        },
        {
            "Day": "Day15",
            "H1_00mm": "D15 1:00 o'Clock",
            "H2_00mm": "D15 2:00 o'Clock",
            "H3_00mm": "D15 3:00 o'Clock",
            "H4_00mm":"D15 4:00 o'Clock",
            "H5_00mm": "D15 5:00 o'Clock",
            "H6_00mm": "D15 6:00 o'Clock",
            "H7_00mm": "D15 7:00 o'Clock",
            "H8_00mm": "D15 8:00 o'Clock",
            "H9_00mm": "D15 9:00 o'Clock",
            "H10_00mm": "D15 10:00 o'Clock",
            "H11_00mm": "D15 11:00 o'Clock",
            "H12_00mm": "D15 12:00 o'Clock"
            
        },
        {
            "Day": "Day16",
            "H1_00mm": "D16 1:00 o'Clock",
            "H2_00mm": "D16 2:00 o'Clock",
            "H3_00mm": "D16 3:00 o'Clock",
            "H4_00mm":"D16 4:00 o'Clock",
            "H5_00mm": "D16 5:00 o'Clock",
            "H6_00mm": "D16 6:00 o'Clock",
            "H7_00mm": "D16 7:00 o'Clock",
            "H8_00mm": "D16 8:00 o'Clock",
            "H9_00mm": "D16 9:00 o'Clock",
            "H10_00mm": "D16 10:00 o'Clock",
            "H11_00mm": "D16 11:00 o'Clock",
            "H12_00mm": "D16 12:00 o'Clock"
            
        },
        {
            "Day": "Day17",
            "H1_00mm": "D17 1:00 o'Clock",
            "H2_00mm": "D17 2:00 o'Clock",
            "H3_00mm": "D17 3:00 o'Clock",
            "H4_00mm":"D17 4:00 o'Clock",
            "H5_00mm": "D17 5:00 o'Clock",
            "H6_00mm": "D17 6:00 o'Clock",
            "H7_00mm": "D17 7:00 o'Clock",
            "H8_00mm": "D17 8:00 o'Clock",
            "H9_00mm": "D17 9:00 o'Clock",
            "H10_00mm": "D17 10:00 o'Clock",
            "H11_00mm": "D17 11:00 o'Clock",
            "H12_00mm": "D17 12:00 o'Clock"
            
        },
        {
            "Day": "Day18",
            "H1_00mm": "D18 1:00 o'Clock",
            "H2_00mm": "D18 2:00 o'Clock",
            "H3_00mm": "D18 3:00 o'Clock",
            "H4_00mm":"D18 4:00 o'Clock",
            "H5_00mm": "D18 5:00 o'Clock",
            "H6_00mm": "D18 6:00 o'Clock",
            "H7_00mm": "D18 7:00 o'Clock",
            "H8_00mm": "D18 8:00 o'Clock",
            "H9_00mm": "D18 9:00 o'Clock",
            "H10_00mm": "D18 10:00 o'Clock",
            "H11_00mm": "D18 11:00 o'Clock",
            "H12_00mm": "D18 12:00 o'Clock"
            
        },
        {
            "Day": "Day19",
            "H1_00mm": "D19 1:00 o'Clock",
            "H2_00mm": "D19 2:00 o'Clock",
            "H3_00mm": "D19 3:00 o'Clock",
            "H4_00mm":"D19 4:00 o'Clock",
            "H5_00mm": "D19 5:00 o'Clock",
            "H6_00mm": "D19 6:00 o'Clock",
            "H7_00mm": "D19 7:00 o'Clock",
            "H8_00mm": "D19 8:00 o'Clock",
            "H9_00mm": "D19 9:00 o'Clock",
            "H10_00mm": "D19 10:00 o'Clock",
            "H11_00mm": "D19 11:00 o'Clock",
            "H12_00mm": "D19 12:00 o'Clock"
            
        },
        {
            "Day": "Day20",
            "H1_00mm": "D20 1:00 o'Clock",
            "H2_00mm": "D20 2:00 o'Clock",
            "H3_00mm": "D20 3:00 o'Clock",
            "H4_00mm":"D20 4:00 o'Clock",
            "H5_00mm": "D20 5:00 o'Clock",
            "H6_00mm": "D20 6:00 o'Clock",
            "H7_00mm": "D20 7:00 o'Clock",
            "H8_00mm": "D20 8:00 o'Clock",
            "H9_00mm": "D20 9:00 o'Clock",
            "H10_00mm": "D20 10:00 o'Clock",
            "H11_00mm": "D20 11:00 o'Clock",
            "H12_00mm": "D20 12:00 o'Clock"
            
        },
        {
            "Day": "Day21",
            "H1_00mm": "D21 1:00 o'Clock",
            "H2_00mm": "D21 2:00 o'Clock",
            "H3_00mm": "D21 3:00 o'Clock",
            "H4_00mm":"D21 4:00 o'Clock",
            "H5_00mm": "D21 5:00 o'Clock",
            "H6_00mm": "D21 6:00 o'Clock",
            "H7_00mm": "D21 7:00 o'Clock",
            "H8_00mm": "D21 8:00 o'Clock",
            "H9_00mm": "D21 9:00 o'Clock",
            "H10_00mm": "D21 10:00 o'Clock",
            "H11_00mm": "D21 11:00 o'Clock",
            "H12_00mm": "D21 12:00 o'Clock"
            
        },
        
        {
            "Day": "Day22",
            "H1_00mm": "D22 1:00 o'Clock",
            "H2_00mm": "D22 2:00 o'Clock",
            "H3_00mm": "D22 3:00 o'Clock",
            "H4_00mm":"D22 4:00 o'Clock",
            "H5_00mm": "D22 5:00 o'Clock",
            "H6_00mm": "D22 6:00 o'Clock",
            "H7_00mm": "D22 7:00 o'Clock",
            "H8_00mm": "D22 8:00 o'Clock",
            "H9_00mm": "D22 9:00 o'Clock",
            "H10_00mm": "D22 10:00 o'Clock",
            "H11_00mm": "D22 11:00 o'Clock",
            "H12_00mm": "D22 12:00 o'Clock"
            
        },
        {
            "Day": "Day23",
            "H1_00mm": "D23 1:00 o'Clock",
            "H2_00mm": "D23 2:00 o'Clock",
            "H3_00mm": "D23 3:00 o'Clock",
            "H4_00mm":"D23 4:00 o'Clock",
            "H5_00mm": "D23 5:00 o'Clock",
            "H6_00mm": "D23 6:00 o'Clock",
            "H7_00mm": "D23 7:00 o'Clock",
            "H8_00mm": "D23 8:00 o'Clock",
            "H9_00mm": "D23 9:00 o'Clock",
            "H10_00mm": "D23 10:00 o'Clock",
            "H11_00mm": "D23 11:00 o'Clock",
            "H12_00mm": "D23 12:00 o'Clock"
            
        }
    ],
    "message": ""
}
